__init__.py
oyez_api_wrapper.py
oyez_api_wrapper-0.0.3.dist-info/LICENSE
oyez_api_wrapper-0.0.3.dist-info/METADATA
oyez_api_wrapper-0.0.3.dist-info/WHEEL
oyez_api_wrapper-0.0.3.dist-info/top_level.txt
oyez_api_wrapper-0.0.3.dist-info/RECORD
