Metadata-Version: 2.1
Name: oyez_api_wrapper
Version: 0.0.3
Summary: A wrapper for the Oyez API
Home-page: https://github.com/tylzars/oyez-api-wrapper
Author: Tyler Zars
Author-email: tyler@zars.me
License: UNKNOWN
Platform: UNKNOWN
Classifier: Programming Language :: Python :: 3
Classifier: License :: OSI Approved :: MIT License
Classifier: Operating System :: OS Independent
License-File: LICENSE
